ExtensiveRoleCheck.py
formatter.py
kubenumerate.py
version.py
kubenumerate-2.0.0.dist-info/licenses/LICENSE
kubenumerate-2.0.0.dist-info/METADATA
kubenumerate-2.0.0.dist-info/WHEEL
kubenumerate-2.0.0.dist-info/entry_points.txt
kubenumerate-2.0.0.dist-info/top_level.txt
kubenumerate-2.0.0.dist-info/RECORD
