Metadata-Version: 2.4
Name: kubenumerate
Version: 2.0.0
Summary: A comprehensive Kubernetes security auditing tool
Home-page: https://github.com/0x5ubt13/kubenumerate
Author: Subtle
Author-email: Subtle <5ubt13@protonmail.com>
Maintainer-email: Subtle <5ubt13@protonmail.com>
License:                     GNU GENERAL PUBLIC LICENSE
Project-URL: Homepage, https://github.com/0x5ubt13/kubenumerate
Project-URL: Documentation, https://github.com/0x5ubt13/kubenumerate#readme
Project-URL: Repository, https://github.com/0x5ubt13/kubenumerate
Project-URL: Bug Tracker, https://github.com/0x5ubt13/kubenumerate/issues
Project-URL: Changelog, https://github.com/0x5ubt13/kubenumerate/releases
Keywords: kubernetes,security,audit,compliance,cis
Classifier: Development Status :: 4 - Beta
Classifier: Intended Audience :: Developers
Classifier: Intended Audience :: System Administrators
Classifier: License :: OSI Approved :: MIT License
Classifier: Operating System :: OS Independent
Classifier: Programming Language :: Python :: 3
Classifier: Programming Language :: Python :: 3.8
Classifier: Programming Language :: Python :: 3.9
Classifier: Programming Language :: Python :: 3.10
Classifier: Programming Language :: Python :: 3.11
Classifier: Programming Language :: Python :: 3.12
Classifier: Topic :: Security
Classifier: Topic :: System :: Systems Administration
Requires-Python: >=3.12
License-File: LICENSE
Requires-Dist: colorama>=0.4.6
Requires-Dist: pandas>=2.2.2
Requires-Dist: requests>=2.32.3
Requires-Dist: PyYAML>=6.0.1
Requires-Dist: packaging>=24.0
Requires-Dist: openpyxl>=3.1.2
Requires-Dist: xlsxwriter>=3.2.0
Requires-Dist: python-docx>=1.1.0
Provides-Extra: dev
Requires-Dist: pytest>=7.0.0; extra == "dev"
Requires-Dist: pytest-cov>=4.0.0; extra == "dev"
Requires-Dist: flake8>=5.0.0; extra == "dev"
Requires-Dist: black>=22.0.0; extra == "dev"
Requires-Dist: mypy>=1.0.0; extra == "dev"
Requires-Dist: bandit>=1.7.0; extra == "dev"
Requires-Dist: safety>=2.0.0; extra == "dev"
Dynamic: author
Dynamic: home-page
Dynamic: license-file
Dynamic: requires-python
